pipeline/__init__.py
pipeline/decorators.py
pipeline/test.py
pipeline/utils.py
python_pipeliner-0.5.1.dist-info/LICENSE
python_pipeliner-0.5.1.dist-info/METADATA
python_pipeliner-0.5.1.dist-info/WHEEL
python_pipeliner-0.5.1.dist-info/top_level.txt
python_pipeliner-0.5.1.dist-info/RECORD
